f2xba/__init__.py
f2xba/_version.py
f2xba/prefixes.py
f2xba/biocyc/__init__.py
f2xba/biocyc/biocyc_data.py
f2xba/biocyc/biocyc_gene.py
f2xba/biocyc/biocyc_protein.py
f2xba/biocyc/biocyc_rna.py
f2xba/ec_model/__init__.py
f2xba/ec_model/ec_model.py
f2xba/ncbi/__init__.py
f2xba/ncbi/ncbi_chromosome.py
f2xba/ncbi/ncbi_data.py
f2xba/ncbi/ncbi_feature.py
f2xba/ncbi/ncbi_ft_record.py
f2xba/ncbi/ncbi_protein.py
f2xba/optimization/__init__.py
f2xba/optimization/ecm_opt.py
f2xba/optimization/ecm_results.py
f2xba/optimization/fba_opt.py
f2xba/optimization/fba_results.py
f2xba/optimization/gecko_fit_kcats.py
f2xba/optimization/optimize.py
f2xba/optimization/rba_fit_kcats.py
f2xba/optimization/rba_initial_assignments.py
f2xba/optimization/rba_opt.py
f2xba/optimization/rba_results.py
f2xba/optimization/results.py
f2xba/rba_model/__init__.py
f2xba/rba_model/initital_assignments.py
f2xba/rba_model/rba_densities.py
f2xba/rba_model/rba_enzymes.py
f2xba/rba_model/rba_macromolecules.py
f2xba/rba_model/rba_medium.py
f2xba/rba_model/rba_metabolism.py
f2xba/rba_model/rba_model.py
f2xba/rba_model/rba_parameters.py
f2xba/rba_model/rba_processes.py
f2xba/rba_model/rba_target_value.py
f2xba/rba_model/rba_targets.py
f2xba/tfa_model/__init__.py
f2xba/tfa_model/td_compartment_data.py
f2xba/tfa_model/td_cue_data.py
f2xba/tfa_model/td_reactant_data.py
f2xba/tfa_model/td_reaction_data.py
f2xba/tfa_model/td_species_data.py
f2xba/tfa_model/tfa_model.py
f2xba/uniprot/__init__.py
f2xba/uniprot/uniprot_data.py
f2xba/uniprot/uniprot_protein.py
f2xba/utils/__init__.py
f2xba/utils/biocyc_utils.py
f2xba/utils/calc_mw.py
f2xba/utils/gpm_utils.py
f2xba/utils/mapping_utils.py
f2xba/utils/rba_utils.py
f2xba/utils/sgko_utils.py
f2xba/utils/tfa_utils.py
f2xba/xba_model/__init__.py
f2xba/xba_model/enzyme.py
f2xba/xba_model/fbc_gene_product.py
f2xba/xba_model/fbc_objective.py
f2xba/xba_model/miriam_annotation.py
f2xba/xba_model/protein.py
f2xba/xba_model/protein_data.py
f2xba/xba_model/sbml_compartment.py
f2xba-1.9.8.dist-info/licenses/LICENSE.txt
f2xba-1.9.8.dist-info/METADATA
f2xba-1.9.8.dist-info/WHEEL
f2xba-1.9.8.dist-info/top_level.txt
f2xba-1.9.8.dist-info/RECORD
