Metadata-Version: 2.4
Name: f2xba
Version: 1.9.8
Summary: f2xba modelling framework: from FBA to extended genome-scale modelling
Home-page: https://www.cs.hhu.de/lehrstuehle-und-arbeitsgruppen/computational-cell-biology
Author: Peter Schubert
Author-email: peter.schubert@hhu.de
License: GPLv3
Project-URL: Source Code, https://github.com/SchubertP/f2xba
Project-URL: Documentation, https://f2xba.readthedocs.io
Project-URL: Bug Tracker, https://github.com/SchubertP/f2xba/issues
Keywords: systems biology,extended metabolic modeling,FBA,GECKO,RBA,TFA,SBML,Gurobi
Classifier: Programming Language :: Python :: 3
Classifier: License :: OSI Approved :: GNU Lesser General Public License v3 (LGPLv3)
Classifier: Operating System :: OS Independent
Classifier: Topic :: Scientific/Engineering :: Bio-Informatics
Requires-Python: >=3.11
License-File: LICENSE.txt
Requires-Dist: pandas>=2.3.0
Requires-Dist: numpy>=2.0.0
Requires-Dist: scipy>=1.11.0
Requires-Dist: requests>=2.30.0
Requires-Dist: matplotlib>=3.6.3
Requires-Dist: sbmlxdf>=1.0.2
Dynamic: author
Dynamic: author-email
Dynamic: classifier
Dynamic: description
Dynamic: description-content-type
Dynamic: home-page
Dynamic: keywords
Dynamic: license
Dynamic: license-file
Dynamic: project-url
Dynamic: requires-dist
Dynamic: requires-python
Dynamic: summary
